odoo9_addon_html_text-9.0.1.0.0-py2.7-nspkg.pth
odoo_addons/html_text/__openerp__.py
odoo_addons/html_text/__init__.py
odoo_addons/html_text/README.rst
odoo_addons/html_text/models/ir_fields_converter.py
odoo_addons/html_text/models/__init__.py
odoo_addons/html_text/tests/__init__.py
odoo_addons/html_text/tests/test_extractor.py
odoo_addons/html_text/static/description/icon.png
odoo9_addon_html_text-9.0.1.0.0.dist-info/top_level.txt
odoo9_addon_html_text-9.0.1.0.0.dist-info/WHEEL
odoo9_addon_html_text-9.0.1.0.0.dist-info/RECORD
odoo9_addon_html_text-9.0.1.0.0.dist-info/metadata.json
odoo9_addon_html_text-9.0.1.0.0.dist-info/DESCRIPTION.rst
odoo9_addon_html_text-9.0.1.0.0.dist-info/METADATA
odoo9_addon_html_text-9.0.1.0.0.dist-info/namespace_packages.txt
